MANIFEST.in
README.rst
setup.py
intervene/__init__.py
intervene/helpers.py
intervene/intervene
intervene.egg-info/PKG-INFO
intervene.egg-info/SOURCES.txt
intervene.egg-info/dependency_links.txt
intervene.egg-info/requires.txt
intervene.egg-info/top_level.txt
intervene/example_data/__init__.py
intervene/example_data/ENCODE_hESC/H3K27ac.bed
intervene/example_data/ENCODE_hESC/H3K27me3.bed
intervene/example_data/ENCODE_hESC/H3K4me1.bed
intervene/example_data/ENCODE_hESC/H3K4me2.bed
intervene/example_data/ENCODE_hESC/H3K4me3.bed
intervene/example_data/ENCODE_hESC/__init__.py
intervene/example_data/Gene_list/Macrophage.txt
intervene/example_data/Gene_list/Myotube.txt
intervene/example_data/Gene_list/Th-cell.txt
intervene/example_data/Gene_list/__init__.py
intervene/example_data/Gene_list/mESC.txt
intervene/example_data/Gene_list/pro-B.txt
intervene/example_data/dbSUPER_mm9/Bone_Marrow.bed
intervene/example_data/dbSUPER_mm9/Cerebellum.bed
intervene/example_data/dbSUPER_mm9/Cortex.bed
intervene/example_data/dbSUPER_mm9/E14.5_Brain.bed
intervene/example_data/dbSUPER_mm9/E14.5_Heart.bed
intervene/example_data/dbSUPER_mm9/E14.5_Limb.bed
intervene/example_data/dbSUPER_mm9/E14.5_Liver.bed
intervene/example_data/dbSUPER_mm9/HFSCs.bed
intervene/example_data/dbSUPER_mm9/Heart.bed
intervene/example_data/dbSUPER_mm9/Intestine.bed
intervene/example_data/dbSUPER_mm9/Kidney.bed
intervene/example_data/dbSUPER_mm9/Liver.bed
intervene/example_data/dbSUPER_mm9/Lung.bed
intervene/example_data/dbSUPER_mm9/MEF.bed
intervene/example_data/dbSUPER_mm9/Macrophage.bed
intervene/example_data/dbSUPER_mm9/Myotubes.bed
intervene/example_data/dbSUPER_mm9/Olfactory_Bulb.bed
intervene/example_data/dbSUPER_mm9/Spleen.bed
intervene/example_data/dbSUPER_mm9/TACs.bed
intervene/example_data/dbSUPER_mm9/Testis.bed
intervene/example_data/dbSUPER_mm9/Th_Cells.bed
intervene/example_data/dbSUPER_mm9/Thymus.bed
intervene/example_data/dbSUPER_mm9/__init__.py
intervene/example_data/dbSUPER_mm9/mESC.bed
intervene/example_data/dbSUPER_mm9/pro-B.bed
intervene/modules/__init__.py
intervene/modules/pairwise/__init__.py
intervene/modules/pairwise/pairwise.py
