Metadata-Version: 1.1
Name: intervene
Version: 0.6.5
Summary: A tool for intersection and visualization of multiple gene or genomic region sets
Home-page: https://github.com/asntech/intervene
Author: Aziz Khan
Author-email: azez.khan@gmail.com
License: MIT
Platform: linux/unix
Classifier: Intended Audience :: Developers
Classifier: Intended Audience :: Science/Research
Classifier: License :: OSI Approved :: MIT License
Classifier: Operating System :: OS Independent
Classifier: Programming Language :: Python
Classifier: Programming Language :: Python :: 2.7
Classifier: Programming Language :: Python :: 3.4
Classifier: Programming Language :: Python :: 3.5
Classifier: Programming Language :: Python :: 3.6
Classifier: Topic :: Scientific/Engineering :: Bio-Informatics
Classifier: Topic :: Software Development :: Libraries :: Python Modules
